everybeam.cpython-310-x86_64-linux-gnu.so
everybeam-0.8.0.data/data/share/everybeam/HamakerHBACoeff.h5
everybeam-0.8.0.data/data/share/everybeam/HamakerLBACoeff.h5
everybeam-0.8.0.data/data/share/everybeam/oskar.h5
everybeam.libs/libboost_date_time-53dec817.so.1.69.0
everybeam.libs/libbz2-a1e77c99.so.1.0.6
everybeam.libs/libcasa_casa-d36db02f.so.8
everybeam.libs/libcasa_fits-c73f3a8d.so.8
everybeam.libs/libcasa_measures-785262d2.so.8
everybeam.libs/libcasa_ms-dc464544.so.8
everybeam.libs/libcasa_scimath-b10e88d2.so.8
everybeam.libs/libcasa_scimath_f-2f3272ae.so.8
everybeam.libs/libcasa_tables-967acc13.so.8
everybeam.libs/libcfitsio-b4c37dff.so.7.3.47
everybeam.libs/libeverybeam-core.so
everybeam.libs/libeverybeam-hamaker.so
everybeam.libs/libeverybeam-oskar.so
everybeam.libs/libeverybeam-skamidbeam.so
everybeam.libs/libeverybeam.so
everybeam.libs/libfftw3-6b983104.so.3.5.5
everybeam.libs/libfftw3_threads-e9a1faec.so.3.5.5
everybeam.libs/libfftw3f-b4465a35.so.3.5.5
everybeam.libs/libfftw3f_threads-96b454f1.so.3.5.5
everybeam.libs/libgfortran-83c28eba.so.5.0.0
everybeam.libs/libgomp-e985bcbb.so.1.0.0
everybeam.libs/libgsl-b64c76bc.so.23.1.0
everybeam.libs/libgslcblas-cd2c2030.so.0.0.0
everybeam.libs/libhdf5-a025a41d.so.200.2.0
everybeam.libs/libhdf5_cpp-f3621b09.so.200.2.0
everybeam.libs/libncurses-38c2e1a3.so.6.1
everybeam.libs/libopenblas-r0-11edc3fa.3.15.so
everybeam.libs/libquadmath-2284e583.so.0.0.0
everybeam.libs/libreadline-69c5979f.so.7.0
everybeam.libs/libtinfo-3a2cb85b.so.6.1
everybeam-0.8.0.dist-info/METADATA
everybeam-0.8.0.dist-info/WHEEL
everybeam-0.8.0.dist-info/RECORD
everybeam-0.8.0.dist-info/licenses/LICENSE
everybeam-0.8.0.dist-info/sboms/auditwheel.cdx.json
