Metadata-Version: 2.2
Name: everybeam
Version: 0.8.0
Summary: EveryBeam
Author-Email: Bram Veenboer <veenboer@astron.nl>, =?utf-8?q?Andr=C3=A9_Offringa?= <offringa@astron.nl>, Sebastiaan van der Tol <tol@astron.nl>, Tammo Jan Dijkema <dijkema@astron.nl>, Jakob Maljaars <jakob.maljaars@stcorp.nl>, Maik Nijhuis <maik.nijhuis@triopsys.nl>
License: GPLv3+
Classifier: Development Status :: 5 - Production/Stable
Classifier: Intended Audience :: Science/Research
Classifier: License :: OSI Approved :: GNU General Public License v3 or later (GPLv3+)
Classifier: Programming Language :: C++
Classifier: Programming Language :: Python :: 3
Classifier: Topic :: Scientific/Engineering :: Astronomy
Project-URL: Homepage, https://git.astron.nl/RD/EveryBeam/
Project-URL: Documentation, https://everybeam.readthedocs.io/
Project-URL: Repository, https://git.astron.nl/RD/EveryBeam.git
Requires-Python: >=3.9
Requires-Dist: numpy
